llm_batch_helper/__init__.py
llm_batch_helper/cache.py
llm_batch_helper/config.py
llm_batch_helper/exceptions.py
llm_batch_helper/input_handlers.py
llm_batch_helper/providers.py
llm_batch_helper-0.4.0.dist-info/LICENSE
llm_batch_helper-0.4.0.dist-info/METADATA
llm_batch_helper-0.4.0.dist-info/WHEEL
llm_batch_helper-0.4.0.dist-info/RECORD
