Metadata-Version: 2.3
Name: llm_batch_helper
Version: 0.4.0
Summary: A Python package that enables batch submission of prompts to LLM APIs, with simplified interface and built-in async capabilities handled implicitly.
License: MIT
Keywords: llm,openai,together,openrouter,gemini,batch,async,ai,nlp,api
Author: Tianyi Peng
Author-email: tianyipeng95@gmail.com
Requires-Python: >=3.10,<4.0
Classifier: Development Status :: 4 - Beta
Classifier: Intended Audience :: Developers
Classifier: License :: OSI Approved :: MIT License
Classifier: Programming Language :: Python :: 3
Classifier: Programming Language :: Python :: 3.10
Classifier: Programming Language :: Python :: 3.11
Classifier: Programming Language :: Python :: 3.12
Classifier: Programming Language :: Python :: 3.13
Classifier: Topic :: Scientific/Engineering :: Artificial Intelligence
Classifier: Topic :: Software Development :: Libraries :: Python Modules
Requires-Dist: google-generativeai (>=0.3.0,<0.4.0)
Requires-Dist: httpx (>=0.24.0,<2.0.0)
Requires-Dist: openai (>=1.0.0,<2.0.0)
Requires-Dist: tenacity (>=8.0.0,<9.0.0)
Requires-Dist: tqdm (>=4.65.0,<5.0.0)
Project-URL: Homepage, https://github.com/TianyiPeng/LLM_batch_helper
Project-URL: Repository, https://github.com/TianyiPeng/LLM_batch_helper
